lebon/__init__.py
lebon/constants.py
lebon/main.py
lebon/utils.py
lebon/assets/data.json
lebon-0.1.5.dist-info/METADATA
lebon-0.1.5.dist-info/WHEEL
lebon-0.1.5.dist-info/entry_points.txt
lebon-0.1.5.dist-info/top_level.txt
lebon-0.1.5.dist-info/RECORD
