Metadata-Version: 2.1
Name: lebon
Version: 0.1.5
Summary: You are my sunshine, my only sunshine.
Author: Lebon James
License: MIT
Classifier: Programming Language :: Python :: 3
Classifier: License :: OSI Approved :: MIT License
Classifier: Operating System :: OS Independent
Requires-Dist: pyperclip
Requires-Dist: google-generativeai
Requires-Dist: pyautogui
